{
    "app_version": "1.0.9",
    "chart_version": "0.1.0",
    "container_port": 8080,
    "helm_template_name": "dash",
    "project_name": "etools-dash",
    "project_desc": "eTools Django Backend Helm Chart",
    "target_environment": ["develop", "staging", "test", "demo", "production"],
    "container_command": "node express.js",
    "container_entrypoint": "",
    "docker_hub_repo": "unicef/etools-pmp",
    "docker_custom_image_tag": "",
    "max_cpu": 1,
    "req_cpu": "500m",
    "max_ram": "1Gi",
    "req_ram": "512Mi",
    "proj_homepage": "https://etools.unicef.org",
    "proj_icon_url": "https://github.com/unicef/etools-tpm/blob/master/src/assets/images/etools_logo_icon.png",
}